setup.cfg
setup.py
seaborn/flask_server/__init__.py
seaborn/flask_server/decorators.py
seaborn/flask_server/global_import.py
seaborn/flask_server/memcache.py
seaborn/flask_server/blueprint/__init__.py
seaborn/flask_server/blueprint/blueprint.py
seaborn/flask_server/blueprint/python_bindings/__init__.py
seaborn/flask_server/blueprint/python_bindings/python_bindings.py
seaborn/flask_server/blueprint/unity_bindings/__init__.py
seaborn/flask_server/blueprint/unity_bindings/unity_bindings.py
seaborn/flask_server/blueprint/unity_bindings/cs_templates/__init__.py
seaborn/flask_server/blueprint/unity_bindings/cs_templates/api_initialize.cs
seaborn/flask_server/blueprint/unity_bindings/cs_templates/api_monitor.cs
seaborn/flask_server/blueprint/unity_bindings/cs_templates/behaviors.cs
seaborn/flask_server/blueprint/unity_bindings/cs_templates/custom_api.cs
seaborn/flask_server/blueprint/unity_bindings/cs_templates/models.cs
seaborn/flask_server/blueprint/unity_bindings/cs_templates/namespace.cs
seaborn/flask_server/blueprint/unity_bindings/cs_templates/operations.cs
seaborn/flask_server/models/__init__.py
seaborn/flask_server/models/models.py
seaborn/flask_server/models/auto_register/__init__.py
seaborn/flask_server/models/auto_register/auto_register.py
seaborn/flask_server/models/auto_register/auto_register_2.py
seaborn/flask_server/models/auto_register/auto_register_3.py
seaborn/flask_server/setup/__init__.py
seaborn/flask_server/setup/config.py
seaborn/flask_server/setup/manager.py
seaborn/flask_server/setup/report.py
seaborn/flask_server/setup/setup_flask.py
seaborn_flask_server.egg-info/PKG-INFO
seaborn_flask_server.egg-info/SOURCES.txt
seaborn_flask_server.egg-info/dependency_links.txt
seaborn_flask_server.egg-info/requires.txt
seaborn_flask_server.egg-info/top_level.txt
test/test_access.py
test/test_account.py
test/test_bindings.py
test/test_echo.py
test/test_intellisense.py
test/test_repr_wrapper.py
test/test_transfer.py
test/test_user.py