Metadata-Version: 1.1
Name: seaborn-flask-server
Version: 0.0.2
Summary: Seaborn helper wrapper around Flask
Home-page: https://github.com/SeabornGames/FlaskServer
Author: Ben Christenson
Author-email: Python@BenChristenson.com
License: MIT License
Platform: UNKNOWN
Classifier: Intended Audience :: Developers
Classifier: Natural Language :: English
Classifier: License :: Other/Proprietary License
Classifier: Operating System :: POSIX :: Linux
Classifier: Programming Language :: Python
Classifier: Programming Language :: Python :: 2.7
